exploited/__init__.py
exploited/exploited.py
exploited-0.1.0.dist-info/METADATA
exploited-0.1.0.dist-info/WHEEL
exploited-0.1.0.dist-info/entry_points.txt
exploited-0.1.0.dist-info/top_level.txt
exploited-0.1.0.dist-info/RECORD
