Metadata-Version: 2.2
Name: exploited
Version: 0.1.0
Summary: An interactive options strategy selector with market analysis
Home-page: https://github.com/lekkshmii
Author: Lekshmi
Author-email: Lekshme2903@gmail.com
License: Apache License 2.0
Classifier: Programming Language :: Python :: 3
Classifier: License :: OSI Approved :: Apache Software License
Classifier: Operating System :: OS Independent
Classifier: Intended Audience :: Developers
Classifier: Topic :: Software Development :: Libraries :: Python Modules
Requires-Python: >=3.7
Requires-Dist: nse-greeks-calculator
Requires-Dist: nsepython
Requires-Dist: numpy
Requires-Dist: pandas
Dynamic: author
Dynamic: author-email
Dynamic: classifier
Dynamic: description
Dynamic: description-content-type
Dynamic: home-page
Dynamic: license
Dynamic: requires-dist
Dynamic: requires-python
Dynamic: summary
